token_limit_guard/__init__.py
token_limit_guard/guard.py
token_limit_guard-0.1.0.dist-info/licenses/LICENSE
token_limit_guard-0.1.0.dist-info/METADATA
token_limit_guard-0.1.0.dist-info/WHEEL
token_limit_guard-0.1.0.dist-info/top_level.txt
token_limit_guard-0.1.0.dist-info/RECORD
