Metadata-Version: 2.4
Name: token-limit-guard
Version: 0.1.0
Summary: Least recently used token allocator with per-token rate limiting
Author-email: Imranur Rahman <ir.shimul@gmail.com>
License: MIT License
Project-URL: Homepage, https://github.com/imranur-rahman/token-limit-guard
Project-URL: Repository, https://github.com/imranur-rahman/token-limit-guard
Project-URL: Issues, https://github.com/imranur-rahman/token-limit-guard/issues
Keywords: tokens,rate-limiting,lru,throttling
Classifier: Development Status :: 3 - Alpha
Classifier: Intended Audience :: Developers
Classifier: License :: OSI Approved :: MIT License
Classifier: Programming Language :: Python
Classifier: Programming Language :: Python :: 3
Classifier: Programming Language :: Python :: 3.9
Classifier: Programming Language :: Python :: 3.10
Classifier: Programming Language :: Python :: 3.11
Classifier: Programming Language :: Python :: 3.12
Classifier: Topic :: Software Development :: Libraries
Classifier: Topic :: System :: Monitoring
Requires-Python: >=3.9
License-File: LICENSE
Provides-Extra: dev
Requires-Dist: pytest>=7.0; extra == "dev"
Dynamic: license-file
